djadmin_ext/__init__.py
djadmin_ext/admin_forms.py
djadmin_ext/helpers.py
djadmin_ext/models.py
djadmin_ext/static/djadmin_ext/admin_ajax.js
djadmin_ext/templates/djadmin_ext/ajax_change_form.html
djadmin_ext/templates/djadmin_ext/ajax_form.html
django_admin_ext-3.0.1.dist-info/licenses/LICENSE
example/sample/__init__.py
example/sample/admin.py
example/sample/models.py
example/sample/tests.py
example/sample/views.py
example/sample/migrations/0001_initial.py
example/sample/migrations/__init__.py
django_admin_ext-3.0.1.dist-info/METADATA
django_admin_ext-3.0.1.dist-info/WHEEL
django_admin_ext-3.0.1.dist-info/top_level.txt
django_admin_ext-3.0.1.dist-info/RECORD
